NiukeChanpinJingliXiaozhao8DaBikaoJinengXiulianZhidaoFix1/README.md
NiukeChanpinJingliXiaozhao8DaBikaoJinengXiulianZhidaoFix1/__init__.py
NiukeChanpinJingliXiaozhao8DaBikaoJinengXiulianZhidaoFix1/__main__.py
NiukeChanpinJingliXiaozhao8DaBikaoJinengXiulianZhidaoFix1/file.epub
NiukeChanpinJingliXiaozhao8DaBikaoJinengXiulianZhidaoFix1/index.html
NiukeChanpinJingliXiaozhao8DaBikaoJinengXiulianZhidaoFix1/css/__init__.py
NiukeChanpinJingliXiaozhao8DaBikaoJinengXiulianZhidaoFix1/css/annotations.css
NiukeChanpinJingliXiaozhao8DaBikaoJinengXiulianZhidaoFix1/css/main.css
NiukeChanpinJingliXiaozhao8DaBikaoJinengXiulianZhidaoFix1/css/normalize.css
NiukeChanpinJingliXiaozhao8DaBikaoJinengXiulianZhidaoFix1/css/popup.css
NiukeChanpinJingliXiaozhao8DaBikaoJinengXiulianZhidaoFix1/font/__init__.py
NiukeChanpinJingliXiaozhao8DaBikaoJinengXiulianZhidaoFix1/font/fontello.eot
NiukeChanpinJingliXiaozhao8DaBikaoJinengXiulianZhidaoFix1/font/fontello.svg
NiukeChanpinJingliXiaozhao8DaBikaoJinengXiulianZhidaoFix1/font/fontello.ttf
NiukeChanpinJingliXiaozhao8DaBikaoJinengXiulianZhidaoFix1/font/fontello.woff
NiukeChanpinJingliXiaozhao8DaBikaoJinengXiulianZhidaoFix1/img/__init__.py
NiukeChanpinJingliXiaozhao8DaBikaoJinengXiulianZhidaoFix1/img/annotator-glyph-sprite.png
NiukeChanpinJingliXiaozhao8DaBikaoJinengXiulianZhidaoFix1/img/annotator-icon-sprite.png
NiukeChanpinJingliXiaozhao8DaBikaoJinengXiulianZhidaoFix1/img/apple-touch-icon.png
NiukeChanpinJingliXiaozhao8DaBikaoJinengXiulianZhidaoFix1/img/cancelfullscreen.png
NiukeChanpinJingliXiaozhao8DaBikaoJinengXiulianZhidaoFix1/img/close.png
NiukeChanpinJingliXiaozhao8DaBikaoJinengXiulianZhidaoFix1/img/fullscreen.png
NiukeChanpinJingliXiaozhao8DaBikaoJinengXiulianZhidaoFix1/img/loader.gif
NiukeChanpinJingliXiaozhao8DaBikaoJinengXiulianZhidaoFix1/img/menu-icon.png
NiukeChanpinJingliXiaozhao8DaBikaoJinengXiulianZhidaoFix1/img/save.png
NiukeChanpinJingliXiaozhao8DaBikaoJinengXiulianZhidaoFix1/img/saved.png
niuke_chanpin_jingli_xiaozhao_8_da_bikao_jineng_xiulian_zhidao_fix1-2025.3.25.1.dist-info/METADATA
niuke_chanpin_jingli_xiaozhao_8_da_bikao_jineng_xiulian_zhidao_fix1-2025.3.25.1.dist-info/WHEEL
niuke_chanpin_jingli_xiaozhao_8_da_bikao_jineng_xiulian_zhidao_fix1-2025.3.25.1.dist-info/entry_points.txt
niuke_chanpin_jingli_xiaozhao_8_da_bikao_jineng_xiulian_zhidao_fix1-2025.3.25.1.dist-info/top_level.txt
niuke_chanpin_jingli_xiaozhao_8_da_bikao_jineng_xiulian_zhidao_fix1-2025.3.25.1.dist-info/RECORD
